SequenceDetector.srcs/sources_1/new/sequencedetector.v
`timescale 1ns / 1ps
//////////////////////////////////////////////////////////////////////////////////
// Company: ApnaSemicoductor
// Engineer: Satvik Goel
// 
// Create Date: 06.01.2023 21:29:15
// Design Name: 
// Module Name: sequencedetector
// Project Name: 
// Target Devices: 
// Tool Versions: 
// Description: 
// 
// Dependencies: 
// 
// Revision:
// Revision 0.01 - File Created
// Additional Comments:
// 
//////////////////////////////////////////////////////////////////////////////////


module sequencedetector(
    input clk,
  	input rst,
  	input in,
  	output reg out
);
  parameter S0 = 2'b00;
  parameter S1 = 2'b01;
  parameter S2 = 2'b10;
  parameter S3 = 2'b11;
  reg [1:0]state;
  always @(posedge clk) begin
    if(rst == 1'b1)begin
      state <= S0;
      out <= 1'b0;
    end
    else begin
      case(state)
        S0: begin
          state <= in ? S0:S1;
          out <= 1'b0;
        end
        S1: begin
          state <= in ? S2:S0;
          out <= 1'b0;
        end
        S2: begin
          state <= in ? S3:S0;
          out <= 1'b0;
        end
        S3: begin
          state <= in ? S0:S0;
          out <= ~in;
        end
      endcase
    end
  end
endmodule

SequenceDetector.srcs/sim_1/new/detect_tb.v
`timescale 1ns / 1ps
//////////////////////////////////////////////////////////////////////////////////
// Company: ApnaSemiconductor
// Engineer: Satvik Goel
// 
// Create Date: 06.01.2023 21:52:25
// Design Name: 
// Module Name: detect_tb
// Project Name: 
// Target Devices: 
// Tool Versions: 
// Description: 
// 
// Dependencies: 
// 
// Revision:
// Revision 0.01 - File Created
// Additional Comments:
// 
//////////////////////////////////////////////////////////////////////////////////


module detect_tb;

reg clk, rst, in;
wire out;
sequencedetector dut(clk,rst,in, out);

initial begin
  clk = 1'b0;
  rst = 1'b1;
  #10 rst = 1'b0;
  in = 1'b0;
end

always begin
  #5 clk = ~clk;
end

initial begin
  $dumpfile("tb.vcd");
  $dumpvars(1,dut);

  #5 in = 1'b0;
  #5 in = 1'b0;
  #5 in = 1'b0;
  #5 in = 1'b1;
  #5 in = 1'b1;
  #5 in = 1'b0;
  #5 in = 1'b1;
  #5 in = 1'b1;
  #5 in = 1'b0;
  #5 in = 1'b0;
  #5 in = 1'b1;
  #5 in = 1'b0;
  #5 in = 1'b0;
  #5 in = 1'b1;
  #5 in = 1'b1;
  #5 in = 1'b0;
  #5 in = 1'b1;
  #5 in = 1'b0;
  #20 $finish;
end
endmodule

SequenceDetector.sim/sim_1/behav/xsim/tb.vcd
$date
   Fri Jan 13 23:43:34 2023
$end
$version
  2018.2
$end
$timescale
  1ps
$end
$scope module detect_tb $end
$scope module dut $end
$var wire 1 ! clk $end
$var wire 1 " rst $end
$var wire 1 # in $end
$var reg 1 $ out $end
$var reg 2 % state [1:0] $end
$var parameter 2 & S0 [1:0] $end
$var parameter 2 ' S1 [1:0] $end
$var parameter 2 ( S2 [1:0] $end
$var parameter 2 ) S3 [1:0] $end
$upscope $end
$upscope $end
$enddefinitions $end
#0
$dumpvars
0!
1"
x#
x$
bx %
b0 &
b1 '
b10 (
b11 )
$end
#5000
1!
0#
0$
b0 %
#10000
0!
0"
#15000
1!
b1 %
#20000
0!
1#
#25000
1!
b10 %
#30000
0!
0#
#35000
1!
1#
b11 %
#40000
0!
#45000
1!
0#
1$
b0 %
#50000
0!
#55000
1!
1#
0$
b0 %
#60000
0!
0#
#65000
1!
b1 %
#70000
0!
1#
#75000
1!
b10 %
#80000
0!
0#
#85000
1!
1#
b11 %
#90000
0!
0#
#95000
1!
1$
b0 %
